youtube_thumbnail_generator/__init__.py
youtube_thumbnail_generator/api_server.py
youtube_thumbnail_generator/final_thumbnail_generator.py
youtube_thumbnail_generator/function_add_chapter.py
youtube_thumbnail_generator/text_png_generator.py
youtube_thumbnail_generator/title_optimizer.py
youtube_thumbnail_generator/youtube_standards.py
youtube_thumbnail_generator-2.6.4.dist-info/licenses/LICENSE
youtube_thumbnail_generator-2.6.4.dist-info/METADATA
youtube_thumbnail_generator-2.6.4.dist-info/WHEEL
youtube_thumbnail_generator-2.6.4.dist-info/entry_points.txt
youtube_thumbnail_generator-2.6.4.dist-info/top_level.txt
youtube_thumbnail_generator-2.6.4.dist-info/RECORD
