Metadata-Version: 2.4
Name: youtube-thumbnail-generator
Version: 2.6.4
Summary: A powerful YouTube thumbnail generator with AI text optimization and multi-language support
Home-page: https://github.com/preangelleo/youtube-thumbnail-generator
Author: preangelleo
Author-email: 
License: MIT
Project-URL: Homepage, https://github.com/preangelleo/youtube-thumbnail-generator
Project-URL: Bug Reports, https://github.com/preangelleo/youtube-thumbnail-generator/issues
Project-URL: Source, https://github.com/preangelleo/youtube-thumbnail-generator
Project-URL: Documentation, https://github.com/preangelleo/youtube-thumbnail-generator/docs
Keywords: youtube,thumbnail,generator,ai,gemini,image,processing
Classifier: Development Status :: 4 - Beta
Classifier: Intended Audience :: Developers
Classifier: Topic :: Multimedia :: Graphics
Classifier: License :: OSI Approved :: MIT License
Classifier: Programming Language :: Python :: 3
Classifier: Programming Language :: Python :: 3.9
Classifier: Programming Language :: Python :: 3.10
Classifier: Programming Language :: Python :: 3.11
Classifier: Operating System :: OS Independent
Requires-Python: >=3.9
License-File: LICENSE
Requires-Dist: Pillow>=10.0.0
Requires-Dist: numpy>=1.24.0
Requires-Dist: python-dotenv>=1.0.0
Requires-Dist: Flask>=2.3.0
Requires-Dist: flask-cors>=4.0.0
Requires-Dist: google-generativeai>=0.3.0
Requires-Dist: langdetect>=1.0.9
Provides-Extra: dev
Requires-Dist: pytest>=7.4.0; extra == "dev"
Requires-Dist: pytest-cov>=4.1.0; extra == "dev"
Requires-Dist: black>=23.7.0; extra == "dev"
Requires-Dist: flake8>=6.1.0; extra == "dev"
Requires-Dist: mypy>=1.5.0; extra == "dev"
Dynamic: home-page
Dynamic: license-file
Dynamic: requires-python
